explain_spike/.ipynb_checkpoints/Classification problem-checkpoint.ipynb
explain_spike/__init__.py
explain_spike/calculate.py
explain_spike/visual.py
explain_spike-0.1.5.dist-info/WHEEL
explain_spike-0.1.5.dist-info/METADATA
explain_spike-0.1.5.dist-info/RECORD
