Metadata-Version: 2.1
Name: explain-spike
Version: 0.1.5
Summary: Package that contains several methods and functions for explaining and understanding machine learning models
Author: Javier Molina Ferreiro
Author-email: javier@spikelab.xyz
Requires-Python: >=3.7,<4.0
Classifier: Programming Language :: Python :: 3
Classifier: Programming Language :: Python :: 3.7
Classifier: Programming Language :: Python :: 3.8
Classifier: Programming Language :: Python :: 3.9
Requires-Dist: alibi (>=0.5.5,<0.6.0)
Requires-Dist: dalex (>=1.0.0,<2.0.0)
Requires-Dist: lightgbm (>=3.1.1,<4.0.0)
Requires-Dist: matplotlib (>=3.3.2,<4.0.0)
Requires-Dist: numpy (>=1.19.2,<2.0.0)
Requires-Dist: pandas (>=1.1.3,<2.0.0)
Requires-Dist: plotly (>=4.14.3,<5.0.0)
Requires-Dist: seaborn (>=0.11.0,<0.12.0)
Requires-Dist: shap (>=0.38.1,<0.39.0)
